colortag/__init__.py
colortag/colortag.py
colortag-0.0.2.dist-info/METADATA
colortag-0.0.2.dist-info/WHEEL
colortag-0.0.2.dist-info/top_level.txt
colortag-0.0.2.dist-info/RECORD
