Metadata-Version: 2.1
Name: colortag
Version: 0.0.2
Summary: Python library for adding ANSI colors to the terminal output using a simple syntax
Author: Wagner Kauê
Author-email: <wkmartinst@gmail.com>
Keywords: python,ansi,colors,color,terminal
Classifier: Development Status :: 4 - Beta
Classifier: Intended Audience :: Developers
Classifier: Programming Language :: Python :: 3
Classifier: Operating System :: Unix
Classifier: Operating System :: MacOS :: MacOS X
Classifier: Operating System :: Microsoft :: Windows
